MANIFEST.in
README.rst
setup.py
requests_nber/__init__.py
requests_nber/nber.py
requests_nber.egg-info/PKG-INFO
requests_nber.egg-info/SOURCES.txt
requests_nber.egg-info/dependency_links.txt
requests_nber.egg-info/not-zip-safe
requests_nber.egg-info/requires.txt
requests_nber.egg-info/top_level.txt