Metadata-Version: 1.0
Name: requests-nber
Version: 0.0.1
Summary: Requests wrapper to log onto NBER.org.
Home-page: http://www.erinhengel.com/software/requests-nber/
Author: Erin Hengel
Author-email: erin@erinhengel.com
License: Apache 2.0
Platform: UNKNOWN
